<?xml version="1.0"?>
<rolemap>

    <permissions>
        <permission name="View" acquire="True">
            <role name="Owner" />
            <role name="Manager" />
            <role name="Site Administrator" />
            <role name="Contributor" />
            <role name="Reader" />
            <role name="Editor" />
        </permission>

        <permission name="tdf.bildungsportal: Add Project" acquire="True">
            <role name="Owner" />
            <role name="Manager" />
            <role name="Site Administrator" />
            <role name="Contributor" />
            <role name="Reader" />
            <role name="Editor" />
            <role name="Member" />
        </permission>
    </permissions>


</rolemap>
